log2s3/__init__.py
log2s3/app.py
log2s3/common_stream.py
log2s3/compr_stream.py
log2s3/main.py
log2s3/processor.py
log2s3/version.py
log2s3-0.8.dist-info/LICENSE
log2s3-0.8.dist-info/METADATA
log2s3-0.8.dist-info/WHEEL
log2s3-0.8.dist-info/entry_points.txt
log2s3-0.8.dist-info/top_level.txt
log2s3-0.8.dist-info/RECORD
