Metadata-Version: 2.1
Name: log2s3
Version: 0.8
Summary: log directory management CLI utility
Home-page: https://github.com/wtnb75/log2s3
Author: Watanabe Takashi
Author-email: wtnb75@gmail.com
License: MIT
Classifier: Development Status :: 3 - Alpha
Classifier: Intended Audience :: Developers
Classifier: License :: OSI Approved :: MIT License
Classifier: Topic :: System :: Networking
Classifier: Programming Language :: Python :: 3
License-File: LICENSE
Requires-Dist: click
Requires-Dist: boto3
Requires-Dist: python-dotenv
Requires-Dist: pytimeparse
Requires-Dist: humanfriendly
Requires-Dist: fastapi
Provides-Extra: ext
Requires-Dist: zstd ; extra == 'ext'
Requires-Dist: lz4 ; extra == 'ext'
Requires-Dist: Brotli ; extra == 'ext'
Requires-Dist: pyliblzfse ; extra == 'ext'
Requires-Dist: zopfli ; extra == 'ext'
Requires-Dist: python-snappy <0.7 ; extra == 'ext'
Requires-Dist: python-lzo ; extra == 'ext'
Requires-Dist: pyzpaq ; extra == 'ext'
Requires-Dist: zlib-ng ; extra == 'ext'
Requires-Dist: PyYAML ; extra == 'ext'
